{
    "annotations": {
        "list": [
            {
                "builtIn": 1,
                "datasource": {
                    "type": "datasource",
                    "uid": "grafana"
                },
                "enable": true,
                "hide": true,
                "iconColor": "rgba(0, 211, 255, 1)",
                "name": "Annotations & Alerts",
                "target": {
                    "limit": 100,
                    "matchAny": false,
                    "tags": [],
                    "type": "dashboard"
                },
                "type": "dashboard"
            }
        ]
    },
    "description": "Metrics from tasmota devices",
    "editable": true,
    "fiscalYearStartMonth": 0,
    "graphTooltip": 2,
    "links": [],
    "liveNow": true,
    "panels": [
        {
            "gridPos": {
                "h": 1,
                "w": 24,
                "x": 0,
                "y": 0
            },
            "id": 113,
            "title": "General",
            "type": "row"
        },
        {
            "datasource": {
                "type": "prometheus",
                "uid": "prometheus"
            },
            "fieldConfig": {
                "defaults": {
                    "color": {
                        "fixedColor": "transparent",
                        "mode": "fixed"
                    },
                    "custom": {
                        "align": "left",
                        "cellOptions": {
                            "mode": "gradient",
                            "type": "color-background"
                        },
                        "inspect": false
                    },
                    "mappings": [
                        {
                            "options": {
                                "0": {
                                    "color": "red",
                                    "index": 1,
                                    "text": "Off"
                                },
                                "1": {
                                    "color": "green",
                                    "index": 0,
                                    "text": "On"
                                }
                            },
                            "type": "value"
                        }
                    ],
                    "thresholds": {
                        "mode": "absolute",
                        "steps": [
                            {
                                "color": "green",
                                "value": null
                            }
                        ]
                    },
                    "unit": "bool_on_off"
                },
                "overrides": [
                    {
                        "matcher": {
                            "id": "byName",
                            "options": "Value #B"
                        },
                        "properties": [
                            {
                                "id": "unit",
                                "value": "s"
                            }
                        ]
                    },
                    {
                        "matcher": {
                            "id": "byName",
                            "options": "Value #C"
                        },
                        "properties": [
                            {
                                "id": "unit",
                                "value": "decbytes"
                            }
                        ]
                    },
                    {
                        "matcher": {
                            "id": "byName",
                            "options": "Value #D"
                        },
                        "properties": [
                            {
                                "id": "unit",
                                "value": "none"
                            }
                        ]
                    },
                    {
                        "matcher": {
                            "id": "byName",
                            "options": "Value #E"
                        },
                        "properties": [
                            {
                                "id": "unit",
                                "value": "none"
                            }
                        ]
                    }
                ]
            },
            "gridPos": {
                "h": 8,
                "w": 24,
                "x": 0,
                "y": 1
            },
            "id": 114,
            "options": {
                "cellHeight": "sm",
                "footer": {
                    "countRows": false,
                    "enablePagination": false,
                    "fields": "",
                    "reducer": ["sum"],
                    "show": false
                },
                "showHeader": true
            },
            "pluginVersion": "11.1.0",
            "targets": [
                {
                    "datasource": {
                        "type": "prometheus",
                        "uid": "prometheus"
                    },
                    "editorMode": "code",
                    "exemplar": false,
                    "expr": "tasmota_relay1_state{instance=~\"$instance\"} * on(instance) group_right(tasmota_info) tasmota_info",
                    "format": "table",
                    "hide": false,
                    "instant": true,
                    "legendFormat": "__auto",
                    "range": false,
                    "refId": "A"
                },
                {
                    "datasource": {
                        "type": "prometheus",
                        "uid": "prometheus"
                    },
                    "editorMode": "code",
                    "exemplar": false,
                    "expr": "tasmota_uptime_seconds{instance=~\"$instance\"} * on(instance) group_right(tasmota_info) tasmota_info",
                    "format": "table",
                    "instant": true,
                    "legendFormat": "__auto",
                    "range": false,
                    "refId": "B"
                },
                {
                    "datasource": {
                        "type": "prometheus",
                        "uid": "prometheus"
                    },
                    "editorMode": "code",
                    "exemplar": false,
                    "expr": "tasmota_memory_free_bytes{instance=~\"$instance\"} * on(instance) group_right(tasmota_info) tasmota_info",
                    "format": "table",
                    "hide": false,
                    "instant": true,
                    "legendFormat": "__auto",
                    "range": false,
                    "refId": "C"
                },
                {
                    "datasource": {
                        "type": "prometheus",
                        "uid": "prometheus"
                    },
                    "editorMode": "code",
                    "exemplar": false,
                    "expr": "tasmota_flash_writes_total{instance=~\"$instance\"} * on(instance) group_right(tasmota_info) tasmota_info",
                    "format": "table",
                    "hide": false,
                    "instant": true,
                    "legendFormat": "__auto",
                    "range": false,
                    "refId": "D"
                },
                {
                    "datasource": {
                        "type": "prometheus",
                        "uid": "prometheus"
                    },
                    "editorMode": "code",
                    "exemplar": false,
                    "expr": "tasmota_boot_count{instance=~\"$instance\"} * on(instance) group_right(tasmota_info) tasmota_info",
                    "format": "table",
                    "hide": false,
                    "instant": true,
                    "legendFormat": "__auto",
                    "range": false,
                    "refId": "E"
                }
            ],
            "title": "Version",
            "transformations": [
                {
                    "id": "merge",
                    "options": {}
                },
                {
                    "id": "organize",
                    "options": {
                        "excludeByName": {
                            "Time": true,
                            "build_timestamp": true,
                            "devicename": true,
                            "image": true,
                            "job": true
                        },
                        "includeByName": {},
                        "indexByName": {
                            "Time": 8,
                            "Value #A": 2,
                            "Value #B": 4,
                            "Value #C": 5,
                            "Value #D": 6,
                            "Value #E": 7,
                            "build_timestamp": 9,
                            "devicename": 10,
                            "friendlyname": 0,
                            "image": 11,
                            "instance": 1,
                            "job": 12,
                            "version": 3
                        },
                        "renameByName": {
                            "Time": "",
                            "Value #A": "State",
                            "Value #B": "Uptime",
                            "Value #C": "Free memory",
                            "Value #D": "Flash writes count",
                            "Value #E": "Boot count",
                            "friendlyname": "Device",
                            "instance": "Instance",
                            "version": "Version"
                        }
                    }
                }
            ],
            "type": "table"
        },
        {
            "datasource": {
                "type": "prometheus",
                "uid": "prometheus"
            },
            "fieldConfig": {
                "defaults": {
                    "color": {
                        "mode": "fixed"
                    },
                    "custom": {
                        "fillOpacity": 80,
                        "hideFrom": {
                            "legend": false,
                            "tooltip": false,
                            "viz": false
                        },
                        "insertNulls": false,
                        "lineWidth": 0,
                        "spanNulls": false
                    },
                    "mappings": [
                        {
                            "options": {
                                "0": {
                                    "color": "red",
                                    "index": 0,
                                    "text": "Off"
                                },
                                "1": {
                                    "color": "green",
                                    "index": 1,
                                    "text": "On"
                                }
                            },
                            "type": "value"
                        }
                    ],
                    "thresholds": {
                        "mode": "absolute",
                        "steps": [
                            {
                                "color": "red",
                                "value": null
                            }
                        ]
                    },
                    "unit": "bool_on_off"
                },
                "overrides": []
            },
            "gridPos": {
                "h": 8,
                "w": 24,
                "x": 0,
                "y": 9
            },
            "id": 17,
            "options": {
                "alignValue": "left",
                "legend": {
                    "displayMode": "list",
                    "placement": "bottom",
                    "showLegend": true
                },
                "mergeValues": false,
                "rowHeight": 0.8,
                "showValue": "auto",
                "tooltip": {
                    "mode": "single",
                    "sort": "none"
                }
            },
            "pluginVersion": "8.5.3",
            "targets": [
                {
                    "datasource": {
                        "type": "prometheus",
                        "uid": "${datasource}"
                    },
                    "editorMode": "code",
                    "exemplar": false,
                    "expr": "tasmota_relay1_state{instance=~\"$instance\"} * on(instance) group_right(tasmota_info) tasmota_info",
                    "format": "time_series",
                    "instant": false,
                    "legendFormat": "{{ friendlyname }}",
                    "range": true,
                    "refId": "A"
                }
            ],
            "title": "State",
            "type": "state-timeline"
        },
        {
            "collapsed": false,
            "gridPos": {
                "h": 1,
                "w": 24,
                "x": 0,
                "y": 17
            },
            "id": 104,
            "panels": [],
            "title": "Energy",
            "type": "row"
        },
        {
            "datasource": {
                "type": "prometheus",
                "uid": "prometheus"
            },
            "fieldConfig": {
                "defaults": {
                    "color": {
                        "mode": "thresholds"
                    },
                    "mappings": [],
                    "thresholds": {
                        "mode": "absolute",
                        "steps": [
                            {
                                "color": "green",
                                "value": null
                            },
                            {
                                "color": "red",
                                "value": 80
                            }
                        ]
                    },
                    "unit": "kwatth"
                },
                "overrides": []
            },
            "gridPos": {
                "h": 4,
                "w": 12,
                "x": 0,
                "y": 18
            },
            "id": 102,
            "options": {
                "colorMode": "value",
                "graphMode": "area",
                "justifyMode": "auto",
                "orientation": "auto",
                "percentChangeColorMode": "standard",
                "reduceOptions": {
                    "calcs": ["lastNotNull"],
                    "fields": "",
                    "values": false
                },
                "showPercentChange": false,
                "textMode": "auto",
                "wideLayout": true
            },
            "pluginVersion": "11.1.0",
            "targets": [
                {
                    "datasource": {
                        "type": "prometheus",
                        "uid": "${datasource}"
                    },
                    "editorMode": "code",
                    "expr": "tasmota_energy_power_kilowatts_daily{instance=~\"$instance\"} * on(instance) group_right(tasmota_info) tasmota_info",
                    "legendFormat": "{{ friendlyname }}",
                    "range": true,
                    "refId": "A"
                }
            ],
            "title": "Energy - Today",
            "type": "stat"
        },
        {
            "datasource": {
                "type": "prometheus",
                "uid": "prometheus"
            },
            "fieldConfig": {
                "defaults": {
                    "color": {
                        "mode": "thresholds"
                    },
                    "mappings": [],
                    "thresholds": {
                        "mode": "absolute",
                        "steps": [
                            {
                                "color": "green",
                                "value": null
                            },
                            {
                                "color": "red",
                                "value": 80
                            }
                        ]
                    },
                    "unit": "kwatth"
                },
                "overrides": []
            },
            "gridPos": {
                "h": 4,
                "w": 12,
                "x": 12,
                "y": 18
            },
            "id": 115,
            "options": {
                "colorMode": "value",
                "graphMode": "area",
                "justifyMode": "auto",
                "orientation": "auto",
                "percentChangeColorMode": "standard",
                "reduceOptions": {
                    "calcs": ["lastNotNull"],
                    "fields": "",
                    "values": false
                },
                "showPercentChange": false,
                "textMode": "auto",
                "wideLayout": true
            },
            "pluginVersion": "11.1.0",
            "targets": [
                {
                    "datasource": {
                        "type": "prometheus",
                        "uid": "${datasource}"
                    },
                    "editorMode": "code",
                    "expr": "delta(tasmota_energy_power_kilowatts_total{instance=~\"$instance\"}[$__range]) * on(instance) group_right(tasmota_info) tasmota_info",
                    "format": "time_series",
                    "interval": "",
                    "legendFormat": "{{ friendlyname }}",
                    "range": true,
                    "refId": "A"
                }
            ],
            "title": "Energy in interval",
            "type": "stat"
        },
        {
            "datasource": {
                "type": "prometheus",
                "uid": "prometheus"
            },
            "fieldConfig": {
                "defaults": {
                    "color": {
                        "mode": "palette-classic"
                    },
                    "custom": {
                        "axisBorderShow": false,
                        "axisCenteredZero": false,
                        "axisColorMode": "text",
                        "axisLabel": "",
                        "axisPlacement": "auto",
                        "fillOpacity": 80,
                        "gradientMode": "hue",
                        "hideFrom": {
                            "legend": false,
                            "tooltip": false,
                            "viz": false
                        },
                        "lineWidth": 1,
                        "scaleDistribution": {
                            "type": "linear"
                        },
                        "thresholdsStyle": {
                            "mode": "off"
                        }
                    },
                    "mappings": [],
                    "thresholds": {
                        "mode": "absolute",
                        "steps": [
                            {
                                "color": "green",
                                "value": null
                            },
                            {
                                "color": "red",
                                "value": 80
                            }
                        ]
                    },
                    "unit": "kwatth"
                },
                "overrides": []
            },
            "gridPos": {
                "h": 12,
                "w": 24,
                "x": 0,
                "y": 22
            },
            "id": 110,
            "options": {
                "barRadius": 0,
                "barWidth": 0.97,
                "fullHighlight": false,
                "groupWidth": 0.7,
                "legend": {
                    "calcs": ["lastNotNull", "min", "mean", "max"],
                    "displayMode": "table",
                    "placement": "right",
                    "showLegend": true
                },
                "orientation": "vertical",
                "showValue": "auto",
                "stacking": "none",
                "tooltip": {
                    "mode": "multi",
                    "sort": "none"
                },
                "xField": "Time",
                "xTickLabelRotation": 0,
                "xTickLabelSpacing": 100
            },
            "pluginVersion": "9.3.0",
            "targets": [
                {
                    "datasource": {
                        "type": "prometheus",
                        "uid": "${datasource}"
                    },
                    "editorMode": "code",
                    "expr": "delta(tasmota_energy_power_kilowatts_total{instance=~\"$instance\"}[1h]) * on(instance) group_right(tasmota_info) tasmota_info",
                    "format": "time_series",
                    "interval": "1h",
                    "legendFormat": "{{ friendlyname }}",
                    "range": true,
                    "refId": "A"
                }
            ],
            "title": "Energy per hour",
            "type": "barchart"
        },
        {
            "datasource": {
                "type": "prometheus",
                "uid": "prometheus"
            },
            "fieldConfig": {
                "defaults": {
                    "color": {
                        "mode": "palette-classic"
                    },
                    "custom": {
                        "axisBorderShow": false,
                        "axisCenteredZero": false,
                        "axisColorMode": "text",
                        "axisLabel": "",
                        "axisPlacement": "auto",
                        "fillOpacity": 80,
                        "gradientMode": "hue",
                        "hideFrom": {
                            "legend": false,
                            "tooltip": false,
                            "viz": false
                        },
                        "lineWidth": 1,
                        "scaleDistribution": {
                            "type": "linear"
                        },
                        "thresholdsStyle": {
                            "mode": "off"
                        }
                    },
                    "mappings": [],
                    "thresholds": {
                        "mode": "absolute",
                        "steps": [
                            {
                                "color": "green",
                                "value": null
                            },
                            {
                                "color": "red",
                                "value": 80
                            }
                        ]
                    },
                    "unit": "kwatth"
                },
                "overrides": []
            },
            "gridPos": {
                "h": 12,
                "w": 24,
                "x": 0,
                "y": 34
            },
            "id": 116,
            "options": {
                "barRadius": 0,
                "barWidth": 0.97,
                "fullHighlight": false,
                "groupWidth": 0.7,
                "legend": {
                    "calcs": ["lastNotNull", "min", "mean", "max"],
                    "displayMode": "table",
                    "placement": "right",
                    "showLegend": true
                },
                "orientation": "auto",
                "showValue": "auto",
                "stacking": "none",
                "tooltip": {
                    "mode": "multi",
                    "sort": "none"
                },
                "xField": "Time",
                "xTickLabelRotation": 0,
                "xTickLabelSpacing": 100
            },
            "pluginVersion": "9.3.0",
            "targets": [
                {
                    "datasource": {
                        "type": "prometheus",
                        "uid": "${datasource}"
                    },
                    "editorMode": "code",
                    "expr": "delta(tasmota_energy_power_kilowatts_total{instance=~\"$instance\"}[1d]) * on(instance) group_right(tasmota_info) tasmota_info",
                    "format": "time_series",
                    "interval": "1d",
                    "legendFormat": "{{ friendlyname }}",
                    "range": true,
                    "refId": "A"
                }
            ],
            "timeFrom": "30d",
            "title": "Energy per day",
            "type": "barchart"
        },
        {
            "datasource": {
                "type": "prometheus",
                "uid": "prometheus"
            },
            "fieldConfig": {
                "defaults": {
                    "color": {
                        "mode": "palette-classic"
                    },
                    "custom": {
                        "axisBorderShow": false,
                        "axisCenteredZero": false,
                        "axisColorMode": "text",
                        "axisLabel": "",
                        "axisPlacement": "auto",
                        "fillOpacity": 80,
                        "gradientMode": "hue",
                        "hideFrom": {
                            "legend": false,
                            "tooltip": false,
                            "viz": false
                        },
                        "lineWidth": 1,
                        "scaleDistribution": {
                            "type": "linear"
                        },
                        "thresholdsStyle": {
                            "mode": "off"
                        }
                    },
                    "mappings": [],
                    "thresholds": {
                        "mode": "absolute",
                        "steps": [
                            {
                                "color": "green",
                                "value": null
                            },
                            {
                                "color": "red",
                                "value": 80
                            }
                        ]
                    },
                    "unit": "kwatth"
                },
                "overrides": []
            },
            "gridPos": {
                "h": 12,
                "w": 24,
                "x": 0,
                "y": 46
            },
            "hideTimeOverride": false,
            "id": 111,
            "options": {
                "barRadius": 0,
                "barWidth": 0.97,
                "fullHighlight": false,
                "groupWidth": 0.7,
                "legend": {
                    "calcs": ["lastNotNull", "min", "mean", "max"],
                    "displayMode": "table",
                    "placement": "right",
                    "showLegend": true
                },
                "orientation": "auto",
                "showValue": "auto",
                "stacking": "none",
                "tooltip": {
                    "mode": "multi",
                    "sort": "none"
                },
                "xField": "Time",
                "xTickLabelRotation": 0,
                "xTickLabelSpacing": 100
            },
            "pluginVersion": "9.3.0",
            "targets": [
                {
                    "datasource": {
                        "type": "prometheus",
                        "uid": "${datasource}"
                    },
                    "editorMode": "code",
                    "exemplar": false,
                    "expr": "delta(tasmota_energy_power_kilowatts_total{instance=~\"$instance\"}[1w]) * on(instance) group_right(tasmota_info) tasmota_info",
                    "instant": false,
                    "interval": "1w",
                    "legendFormat": "{{ friendlyname }}",
                    "range": true,
                    "refId": "A"
                }
            ],
            "timeFrom": "3M",
            "title": "Energy per week",
            "type": "barchart"
        },
        {
            "collapsed": false,
            "gridPos": {
                "h": 1,
                "w": 24,
                "x": 0,
                "y": 58
            },
            "id": 12,
            "panels": [],
            "title": "Power",
            "type": "row"
        },
        {
            "datasource": {
                "type": "prometheus",
                "uid": "prometheus"
            },
            "fieldConfig": {
                "defaults": {
                    "color": {
                        "mode": "palette-classic"
                    },
                    "custom": {
                        "axisBorderShow": false,
                        "axisCenteredZero": false,
                        "axisColorMode": "text",
                        "axisLabel": "",
                        "axisPlacement": "auto",
                        "barAlignment": 0,
                        "drawStyle": "line",
                        "fillOpacity": 0,
                        "gradientMode": "none",
                        "hideFrom": {
                            "legend": false,
                            "tooltip": false,
                            "viz": false
                        },
                        "insertNulls": false,
                        "lineInterpolation": "linear",
                        "lineWidth": 1,
                        "pointSize": 5,
                        "scaleDistribution": {
                            "type": "linear"
                        },
                        "showPoints": "auto",
                        "spanNulls": false,
                        "stacking": {
                            "group": "A",
                            "mode": "none"
                        },
                        "thresholdsStyle": {
                            "mode": "off"
                        }
                    },
                    "mappings": [],
                    "thresholds": {
                        "mode": "absolute",
                        "steps": [
                            {
                                "color": "green",
                                "value": null
                            },
                            {
                                "color": "red",
                                "value": 80
                            }
                        ]
                    },
                    "unit": "watt"
                },
                "overrides": []
            },
            "gridPos": {
                "h": 7,
                "w": 8,
                "x": 0,
                "y": 59
            },
            "id": 100,
            "options": {
                "legend": {
                    "calcs": [],
                    "displayMode": "list",
                    "placement": "bottom",
                    "showLegend": true
                },
                "tooltip": {
                    "mode": "multi",
                    "sort": "none"
                }
            },
            "targets": [
                {
                    "datasource": {
                        "type": "prometheus",
                        "uid": "${datasource}"
                    },
                    "editorMode": "code",
                    "expr": "tasmota_energy_power_active_watts{instance=~\"$instance\"} * on(instance) group_right(tasmota_info) tasmota_info",
                    "legendFormat": "{{ friendlyname }}",
                    "range": true,
                    "refId": "A"
                }
            ],
            "title": "Power",
            "type": "timeseries"
        },
        {
            "datasource": {
                "type": "prometheus",
                "uid": "prometheus"
            },
            "fieldConfig": {
                "defaults": {
                    "color": {
                        "mode": "palette-classic"
                    },
                    "custom": {
                        "axisBorderShow": false,
                        "axisCenteredZero": false,
                        "axisColorMode": "text",
                        "axisLabel": "",
                        "axisPlacement": "auto",
                        "barAlignment": 0,
                        "drawStyle": "line",
                        "fillOpacity": 0,
                        "gradientMode": "none",
                        "hideFrom": {
                            "legend": false,
                            "tooltip": false,
                            "viz": false
                        },
                        "insertNulls": false,
                        "lineInterpolation": "linear",
                        "lineWidth": 1,
                        "pointSize": 5,
                        "scaleDistribution": {
                            "type": "linear"
                        },
                        "showPoints": "auto",
                        "spanNulls": false,
                        "stacking": {
                            "group": "A",
                            "mode": "none"
                        },
                        "thresholdsStyle": {
                            "mode": "off"
                        }
                    },
                    "mappings": [],
                    "thresholds": {
                        "mode": "absolute",
                        "steps": [
                            {
                                "color": "green",
                                "value": null
                            },
                            {
                                "color": "red",
                                "value": 80
                            }
                        ]
                    },
                    "unit": "amp"
                },
                "overrides": []
            },
            "gridPos": {
                "h": 7,
                "w": 8,
                "x": 8,
                "y": 59
            },
            "id": 14,
            "options": {
                "legend": {
                    "calcs": [],
                    "displayMode": "list",
                    "placement": "bottom",
                    "showLegend": true
                },
                "tooltip": {
                    "mode": "multi",
                    "sort": "none"
                }
            },
            "targets": [
                {
                    "datasource": {
                        "type": "prometheus",
                        "uid": "xTTLQ3C7z"
                    },
                    "editorMode": "code",
                    "expr": "tasmota_energy_current_amperes{instance=~\"$instance\"} * on(instance) group_right(tasmota_info) tasmota_info",
                    "legendFormat": "{{ friendlyname }}",
                    "range": true,
                    "refId": "A"
                }
            ],
            "title": "Current",
            "type": "timeseries"
        },
        {
            "datasource": {
                "type": "prometheus",
                "uid": "prometheus"
            },
            "fieldConfig": {
                "defaults": {
                    "color": {
                        "mode": "palette-classic"
                    },
                    "custom": {
                        "axisBorderShow": false,
                        "axisCenteredZero": false,
                        "axisColorMode": "text",
                        "axisLabel": "",
                        "axisPlacement": "auto",
                        "barAlignment": 0,
                        "drawStyle": "line",
                        "fillOpacity": 0,
                        "gradientMode": "none",
                        "hideFrom": {
                            "legend": false,
                            "tooltip": false,
                            "viz": false
                        },
                        "insertNulls": false,
                        "lineInterpolation": "linear",
                        "lineWidth": 1,
                        "pointSize": 5,
                        "scaleDistribution": {
                            "type": "linear"
                        },
                        "showPoints": "auto",
                        "spanNulls": false,
                        "stacking": {
                            "group": "A",
                            "mode": "none"
                        },
                        "thresholdsStyle": {
                            "mode": "off"
                        }
                    },
                    "mappings": [],
                    "thresholds": {
                        "mode": "absolute",
                        "steps": [
                            {
                                "color": "green",
                                "value": null
                            },
                            {
                                "color": "red",
                                "value": 80
                            }
                        ]
                    },
                    "unit": "volt"
                },
                "overrides": []
            },
            "gridPos": {
                "h": 7,
                "w": 8,
                "x": 16,
                "y": 59
            },
            "id": 16,
            "options": {
                "legend": {
                    "calcs": [],
                    "displayMode": "list",
                    "placement": "bottom",
                    "showLegend": true
                },
                "tooltip": {
                    "mode": "multi",
                    "sort": "none"
                }
            },
            "targets": [
                {
                    "datasource": {
                        "type": "prometheus",
                        "uid": "${datasource}"
                    },
                    "editorMode": "code",
                    "expr": "tasmota_energy_voltage_volts{instance=~\"$instance\"} * on(instance) group_right(tasmota_info) tasmota_info",
                    "legendFormat": "{{ friendlyname }}",
                    "range": true,
                    "refId": "A"
                }
            ],
            "title": "Voltage",
            "type": "timeseries"
        },
        {
            "datasource": {
                "type": "prometheus",
                "uid": "prometheus"
            },
            "fieldConfig": {
                "defaults": {
                    "color": {
                        "mode": "palette-classic"
                    },
                    "custom": {
                        "axisBorderShow": false,
                        "axisCenteredZero": false,
                        "axisColorMode": "text",
                        "axisLabel": "",
                        "axisPlacement": "auto",
                        "barAlignment": 0,
                        "drawStyle": "line",
                        "fillOpacity": 0,
                        "gradientMode": "none",
                        "hideFrom": {
                            "legend": false,
                            "tooltip": false,
                            "viz": false
                        },
                        "insertNulls": false,
                        "lineInterpolation": "linear",
                        "lineWidth": 1,
                        "pointSize": 5,
                        "scaleDistribution": {
                            "type": "linear"
                        },
                        "showPoints": "auto",
                        "spanNulls": false,
                        "stacking": {
                            "group": "A",
                            "mode": "none"
                        },
                        "thresholdsStyle": {
                            "mode": "off"
                        }
                    },
                    "mappings": [],
                    "thresholds": {
                        "mode": "absolute",
                        "steps": [
                            {
                                "color": "green",
                                "value": null
                            },
                            {
                                "color": "red",
                                "value": 80
                            }
                        ]
                    },
                    "unit": "voltampreact"
                },
                "overrides": []
            },
            "gridPos": {
                "h": 7,
                "w": 8,
                "x": 0,
                "y": 66
            },
            "id": 19,
            "options": {
                "legend": {
                    "calcs": [],
                    "displayMode": "list",
                    "placement": "bottom",
                    "showLegend": true
                },
                "tooltip": {
                    "mode": "multi",
                    "sort": "none"
                }
            },
            "targets": [
                {
                    "datasource": {
                        "type": "prometheus",
                        "uid": "${datasource}"
                    },
                    "editorMode": "code",
                    "expr": "tasmota_sensors_reactivepower_{instance=~\"$instance\"} * on(instance) group_right(tasmota_info) tasmota_info",
                    "legendFormat": "{{ friendlyname }}",
                    "range": true,
                    "refId": "A"
                }
            ],
            "title": "Reactive Power",
            "type": "timeseries"
        },
        {
            "datasource": {
                "type": "prometheus",
                "uid": "prometheus"
            },
            "fieldConfig": {
                "defaults": {
                    "color": {
                        "mode": "palette-classic"
                    },
                    "custom": {
                        "axisBorderShow": false,
                        "axisCenteredZero": false,
                        "axisColorMode": "text",
                        "axisLabel": "",
                        "axisPlacement": "auto",
                        "barAlignment": 0,
                        "drawStyle": "line",
                        "fillOpacity": 0,
                        "gradientMode": "none",
                        "hideFrom": {
                            "legend": false,
                            "tooltip": false,
                            "viz": false
                        },
                        "insertNulls": false,
                        "lineInterpolation": "linear",
                        "lineWidth": 1,
                        "pointSize": 5,
                        "scaleDistribution": {
                            "type": "linear"
                        },
                        "showPoints": "auto",
                        "spanNulls": false,
                        "stacking": {
                            "group": "A",
                            "mode": "none"
                        },
                        "thresholdsStyle": {
                            "mode": "off"
                        }
                    },
                    "mappings": [],
                    "thresholds": {
                        "mode": "absolute",
                        "steps": [
                            {
                                "color": "green",
                                "value": null
                            },
                            {
                                "color": "red",
                                "value": 80
                            }
                        ]
                    },
                    "unit": "voltamp"
                },
                "overrides": []
            },
            "gridPos": {
                "h": 7,
                "w": 8,
                "x": 8,
                "y": 66
            },
            "id": 18,
            "options": {
                "legend": {
                    "calcs": [],
                    "displayMode": "list",
                    "placement": "bottom",
                    "showLegend": true
                },
                "tooltip": {
                    "mode": "multi",
                    "sort": "none"
                }
            },
            "targets": [
                {
                    "datasource": {
                        "type": "prometheus",
                        "uid": "${datasource}"
                    },
                    "editorMode": "code",
                    "expr": "tasmota_sensors_apparentpower_{instance=~\"$instance\"} * on(instance) group_right(tasmota_info) tasmota_info",
                    "legendFormat": "{{ friendlyname }}",
                    "range": true,
                    "refId": "A"
                }
            ],
            "title": "Apparent Power",
            "type": "timeseries"
        },
        {
            "datasource": {
                "type": "prometheus",
                "uid": "prometheus"
            },
            "fieldConfig": {
                "defaults": {
                    "color": {
                        "mode": "palette-classic"
                    },
                    "custom": {
                        "axisBorderShow": false,
                        "axisCenteredZero": false,
                        "axisColorMode": "text",
                        "axisLabel": "",
                        "axisPlacement": "auto",
                        "barAlignment": 0,
                        "drawStyle": "line",
                        "fillOpacity": 0,
                        "gradientMode": "none",
                        "hideFrom": {
                            "legend": false,
                            "tooltip": false,
                            "viz": false
                        },
                        "insertNulls": false,
                        "lineInterpolation": "linear",
                        "lineWidth": 1,
                        "pointSize": 5,
                        "scaleDistribution": {
                            "type": "linear"
                        },
                        "showPoints": "auto",
                        "spanNulls": false,
                        "stacking": {
                            "group": "A",
                            "mode": "none"
                        },
                        "thresholdsStyle": {
                            "mode": "off"
                        }
                    },
                    "decimals": 2,
                    "mappings": [],
                    "thresholds": {
                        "mode": "absolute",
                        "steps": [
                            {
                                "color": "green",
                                "value": null
                            }
                        ]
                    },
                    "unit": "none"
                },
                "overrides": []
            },
            "gridPos": {
                "h": 7,
                "w": 8,
                "x": 16,
                "y": 66
            },
            "id": 20,
            "options": {
                "legend": {
                    "calcs": [],
                    "displayMode": "list",
                    "placement": "bottom",
                    "showLegend": true
                },
                "tooltip": {
                    "mode": "multi",
                    "sort": "none"
                }
            },
            "targets": [
                {
                    "datasource": {
                        "type": "prometheus",
                        "uid": "${datasource}"
                    },
                    "editorMode": "code",
                    "expr": "tasmota_sensors_factor_{instance=~\"$instance\"} * on(instance) group_right(tasmota_info) tasmota_info",
                    "legendFormat": "{{ friendlyname }}",
                    "range": true,
                    "refId": "A"
                }
            ],
            "title": "Power Factor",
            "type": "timeseries"
        },
        {
            "collapsed": false,
            "gridPos": {
                "h": 1,
                "w": 24,
                "x": 0,
                "y": 73
            },
            "id": 5,
            "panels": [],
            "title": "WiFi",
            "type": "row"
        },
        {
            "datasource": {
                "type": "prometheus",
                "uid": "prometheus"
            },
            "fieldConfig": {
                "defaults": {
                    "color": {
                        "mode": "palette-classic"
                    },
                    "custom": {
                        "axisBorderShow": false,
                        "axisCenteredZero": false,
                        "axisColorMode": "text",
                        "axisLabel": "",
                        "axisPlacement": "auto",
                        "barAlignment": 0,
                        "drawStyle": "line",
                        "fillOpacity": 0,
                        "gradientMode": "none",
                        "hideFrom": {
                            "legend": false,
                            "tooltip": false,
                            "viz": false
                        },
                        "insertNulls": false,
                        "lineInterpolation": "linear",
                        "lineWidth": 1,
                        "pointSize": 5,
                        "scaleDistribution": {
                            "type": "linear"
                        },
                        "showPoints": "auto",
                        "spanNulls": false,
                        "stacking": {
                            "group": "A",
                            "mode": "none"
                        },
                        "thresholdsStyle": {
                            "mode": "off"
                        }
                    },
                    "mappings": [],
                    "thresholds": {
                        "mode": "absolute",
                        "steps": [
                            {
                                "color": "green",
                                "value": null
                            },
                            {
                                "color": "red",
                                "value": 80
                            }
                        ]
                    },
                    "unit": "dBm"
                },
                "overrides": []
            },
            "gridPos": {
                "h": 8,
                "w": 24,
                "x": 0,
                "y": 74
            },
            "id": 2,
            "options": {
                "legend": {
                    "calcs": [],
                    "displayMode": "list",
                    "placement": "bottom",
                    "showLegend": true
                },
                "tooltip": {
                    "mode": "multi",
                    "sort": "none"
                }
            },
            "targets": [
                {
                    "datasource": {
                        "type": "prometheus",
                        "uid": "${datasource}"
                    },
                    "editorMode": "code",
                    "expr": "tasmota_wifi_station_signal_dbm{instance=~\"$instance\"} * on(instance) group_right(tasmota_info) tasmota_info",
                    "legendFormat": "{{ friendlyname }}",
                    "range": true,
                    "refId": "A"
                }
            ],
            "title": "Signal",
            "type": "timeseries"
        }
    ],
    "refresh": "10s",
    "schemaVersion": 39,
    "tags": ["tasmota"],
    "templating": {
        "list": [
            {
                "current": {
                    "selected": true,
                    "text": ["All"],
                    "value": ["$__all"]
                },
                "datasource": {
                    "type": "prometheus",
                    "uid": "prometheus"
                },
                "definition": "label_values(tasmota_info,friendlyname)",
                "hide": 0,
                "includeAll": true,
                "label": "Device",
                "multi": true,
                "name": "device",
                "options": [],
                "query": {
                    "qryType": 1,
                    "query": "label_values(tasmota_info,friendlyname)",
                    "refId": "PrometheusVariableQueryEditor-VariableQuery"
                },
                "refresh": 1,
                "regex": "",
                "skipUrlSync": false,
                "sort": 0,
                "type": "query"
            },
            {
                "current": {
                    "selected": true,
                    "text": ["All"],
                    "value": ["$__all"]
                },
                "datasource": {
                    "type": "prometheus",
                    "uid": "prometheus"
                },
                "definition": "label_values(tasmota_info{friendlyname=~\"$device\"},instance)",
                "hide": 0,
                "includeAll": true,
                "label": "Instance",
                "multi": true,
                "name": "instance",
                "options": [],
                "query": {
                    "qryType": 1,
                    "query": "label_values(tasmota_info{friendlyname=~\"$device\"},instance)",
                    "refId": "PrometheusVariableQueryEditor-VariableQuery"
                },
                "refresh": 1,
                "regex": "",
                "skipUrlSync": false,
                "sort": 0,
                "type": "query"
            }
        ]
    },
    "time": {
        "from": "now-6h",
        "to": "now"
    },
    "title": "Tasmota"
}
